{
  "webhooks": {
    "rocket": "https://discord.com/api/webhooks/123456789/abcdefghijk",
    "news": "https://discord.com/api/webhooks/987654321/zyxwvutsrqp",
    "urgent": "https://discord.com/api/webhooks/555555555/mnopqrstuv"
  },
  "thresholds": {
    "l1": {
      "price": 5,
      "volume": 100000
    },
    "l2": {
      "price": 15,
      "volume": 250000
    },
    "l3": {
      "price": 30,
      "volume": 750000
    },
    "l4": {
      "price": 75,
      "volume": 2500000
    }
  },
  "scanInterval": 60,
  "volumeMultiplier": 10,
  "premarketEnabled": true,
  "afterhoursEnabled": true,
  "newsEnabled": true,
  "haltEnabled": true
}